Workbook

Sheet Quarterly Data
A1: Quarter End | B1: Sales (Rs cr) | C1: Expenses (Rs cr) | D1: Op. Profit (Rs cr) | E1: OPM % | F1: Other Income (Rs cr) | G1: Interest (Rs cr) | H1: Depreciation (Rs cr) | I1: PBT (Rs cr) | J1: Tax % | K1: Net Profit (Rs cr)
A2: 2023-06-30 | B2: 128.77 | C2: 104.55 | D2: 24.22 | E2: 18.81 | F2: 1.2 | G2: 5.6 | H2: 13.61 | I2: 6.21 | J2: 45.57 | K2: 3.38
A3: 2023-09-30 | B3: 124.02 | C3: 100.01 | D3: 24.01 | E3: 19.36 | F3: 1.53 | G3: 6.05 | H3: 14.83 | I3: 4.66 | J3: 37.12 | K3: 2.93
A4: 2023-12-31 | B4: 124.05 | C4: 97.72 | D4: 26.33 | E4: 21.23 | F4: 1.17 | G4: 5.86 | H4: 15.1 | I4: 6.54 | J4: 35.02 | K4: 4.25
A5: 2024-03-31 | B5: 126.54 | C5: 99.54 | D5: 27 | E5: 21.34 | F5: 2.86 | G5: 6.29 | H5: 15.73 | I5: 7.84 | J5: 72.58 | K5: 2.15
A6: 2024-06-30 | B6: 140.23 | C6: 116.79 | D6: 23.44 | E6: 16.72 | F6: 0.77 | G6: 5.98 | H6: 15.71 | I6: 2.52 | J6: 28.97 | K6: 1.79
A7: 2024-09-30 | B7: 143.45 | C7: 121.42 | D7: 22.03 | E7: 15.36 | F7: 1.07 | G7: 6.33 | H7: 15.93 | I7: 0.84 | J7: 26.19 | K7: 0.61
A8: 2024-12-31 | B8: 131.85 | C8: 112.09 | D8: 19.76 | E8: 14.99 | F8: 2.07 | G8: 6.35 | H8: 16.09 | I8: -0.61 | J8: -1.64 | K8: -0.61
A9: 2025-03-31 | B9: 137.01 | C9: 112.96 | D9: 24.05 | E9: 17.55 | F9: 0.33 | G9: 5.78 | H9: 15.34 | I9: 3.26 | J9: -19.94 | K9: 3.9
A10: 2025-06-30 | B10: 162.7 | C10: 138.35 | D10: 24.35 | E10: 14.97 | F10: 0.74 | G10: 5.63 | H10: 15.51 | I10: 3.95 | J10: 35.44 | K10: 2.54
A11: 2025-09-30 | B11: 155.65 | C11: 135.66 | D11: 19.99 | E11: 12.84 | F11: 0.57 | G11: 7.41 | H11: 17.38 | I11: -4.23 | J11: -30.97 | K11: -2.91
A12: 2025-12-31 | B12: 143.72 | C12: 120.94 | D12: 22.78 | E12: 15.85 | F12: -1.48 | G12: 7.07 | H12: 17.42 | I12: -3.19 | J12: -41.38 | K12: -1.87
A13: 2026-03-31 | B13: 142.31 | C13: 118.52 | D13: 23.79 | E13: 16.72 | F13: 1.06 | G13: 6.65 | H13: 17.28 | I13: 0.92 | J13: -502.17 | K13: 5.54
A14: 2026-06-30 | B14: 177.68 | C14: 149.07 | D14: 28.61 | E14: 16.1 | F14: 2.32 | G14: 6.52 | H14: 17.38 | I14: 7.03 | J14: 35.42 | K14: 4.55
A16: Source: screener.in, aggregated from NSE filings (quarterly results)

Sheet Growth Analysis
A1: Quarter End | B1: Sales (Rs cr) | C1: QoQ Growth % | D1: YoY Growth % | E1: Net Margin %
A2: ='Quarterly Data'!A2 -> 2023-06-30 | B2: ='Quarterly Data'!B2 -> 128.77 | E2: ='Quarterly Data'!K2/'Quarterly Data'!B2 -> 0.02624835
A3: ='Quarterly Data'!A3 -> 2023-09-30 | B3: ='Quarterly Data'!B3 -> 124.02 | C3: =IFERROR((B3-B2)/B2,"") -> -0.036887474 | E3: ='Quarterly Data'!K3/'Quarterly Data'!B3 -> 0.023625222
A4: ='Quarterly Data'!A4 -> 2023-12-31 | B4: ='Quarterly Data'!B4 -> 124.05 | C4: =IFERROR((B4-B3)/B3,"") -> 0.00024189647 | E4: ='Quarterly Data'!K4/'Quarterly Data'!B4 -> 0.034260379
A5: ='Quarterly Data'!A5 -> 2024-03-31 | B5: ='Quarterly Data'!B5 -> 126.54 | C5: =IFERROR((B5-B4)/B4,"") -> 0.020072551 | E5: ='Quarterly Data'!K5/'Quarterly Data'!B5 -> 0.016990675
A6: ='Quarterly Data'!A6 -> 2024-06-30 | B6: ='Quarterly Data'!B6 -> 140.23 | C6: =IFERROR((B6-B5)/B5,"") -> 0.10818713 | D6: =IFERROR((B6-B2)/B2,"") -> 0.088995884 | E6: ='Quarterly Data'!K6/'Quarterly Data'!B6 -> 0.012764744
A7: ='Quarterly Data'!A7 -> 2024-09-30 | B7: ='Quarterly Data'!B7 -> 143.45 | C7: =IFERROR((B7-B6)/B6,"") -> 0.022962276 | D7: =IFERROR((B7-B3)/B3,"") -> 0.15666828 | E7: ='Quarterly Data'!K7/'Quarterly Data'!B7 -> 0.0042523527
A8: ='Quarterly Data'!A8 -> 2024-12-31 | B8: ='Quarterly Data'!B8 -> 131.85 | C8: =IFERROR((B8-B7)/B7,"") -> -0.080864413 | D8: =IFERROR((B8-B4)/B4,"") -> 0.062877872 | E8: ='Quarterly Data'!K8/'Quarterly Data'!B8 -> -0.0046264695
A9: ='Quarterly Data'!A9 -> 2025-03-31 | B9: ='Quarterly Data'!B9 -> 137.01 | C9: =IFERROR((B9-B8)/B8,"") -> 0.039135381 | D9: =IFERROR((B9-B5)/B5,"") -> 0.082740635 | E9: ='Quarterly Data'!K9/'Quarterly Data'!B9 -> 0.028465076
A10: ='Quarterly Data'!A10 -> 2025-06-30 | B10: ='Quarterly Data'!B10 -> 162.7 | C10: =IFERROR((B10-B9)/B9,"") -> 0.18750456 | D10: =IFERROR((B10-B6)/B6,"") -> 0.16023675 | E10: ='Quarterly Data'!K10/'Quarterly Data'!B10 -> 0.015611555
A11: ='Quarterly Data'!A11 -> 2025-09-30 | B11: ='Quarterly Data'!B11 -> 155.65 | C11: =IFERROR((B11-B10)/B10,"") -> -0.043331285 | D11: =IFERROR((B11-B7)/B7,"") -> 0.085047055 | E11: ='Quarterly Data'!K11/'Quarterly Data'!B11 -> -0.018695792
A12: ='Quarterly Data'!A12 -> 2025-12-31 | B12: ='Quarterly Data'!B12 -> 143.72 | C12: =IFERROR((B12-B11)/B11,"") -> -0.076646322 | D12: =IFERROR((B12-B8)/B8,"") -> 0.090026545 | E12: ='Quarterly Data'!K12/'Quarterly Data'!B12 -> -0.013011411
A13: ='Quarterly Data'!A13 -> 2026-03-31 | B13: ='Quarterly Data'!B13 -> 142.31 | C13: =IFERROR((B13-B12)/B12,"") -> -0.0098107431 | D13: =IFERROR((B13-B9)/B9,"") -> 0.038683308 | E13: ='Quarterly Data'!K13/'Quarterly Data'!B13 -> 0.038929098
A14: ='Quarterly Data'!A14 -> 2026-06-30 | B14: ='Quarterly Data'!B14 -> 177.68 | C14: =IFERROR((B14-B13)/B13,"") -> 0.24854192 | D14: =IFERROR((B14-B10)/B10,"") -> 0.092071297 | E14: ='Quarterly Data'!K14/'Quarterly Data'!B14 -> 0.025607834

Sheet Regression Summary
A1: Linear trend regression: Sales (Rs cr) ~ Quarter Index
A3: Quarter Index | B3: Sales (Rs cr) | D3: Metric | E3: Value
A4: 1 | B4: ='Quarterly Data'!B2 -> 128.77 | D4: Slope (Rs cr / quarter) | E4: =SLOPE(B4:B16,A4:A16) -> 3.2385714
A5: 2 | B5: ='Quarterly Data'!B3 -> 124.02 | D5: Intercept (Rs cr) | E5: =INTERCEPT(B4:B16,A4:A16) -> 118.71308
A6: 3 | B6: ='Quarterly Data'!B4 -> 124.05 | D6: R-squared | E6: =RSQ(B4:B16,A4:A16) -> 0.62003417
A7: 4 | B7: ='Quarterly Data'!B5 -> 126.54 | D7: Correlation (r) | E7: =CORREL(B4:B16,A4:A16) -> 0.78742248
A8: 5 | B8: ='Quarterly Data'!B6 -> 140.23 | D8: Forecast, next quarter (idx 14) | E8: =FORECAST(A16+1,B4:B16,A4:A16) -> 164.05308
A9: 6 | B9: ='Quarterly Data'!B7 -> 143.45
A10: 7 | B10: ='Quarterly Data'!B8 -> 131.85 | D10: Note: matches the Python OLS regression in python/analysis.py (statsmodels) -- same slope, intercept and R-squared, computed independently here with Excel's built-in stats functions.
A11: 8 | B11: ='Quarterly Data'!B9 -> 137.01
A12: 9 | B12: ='Quarterly Data'!B10 -> 162.7
A13: 10 | B13: ='Quarterly Data'!B11 -> 155.65
A14: 11 | B14: ='Quarterly Data'!B12 -> 143.72
A15: 12 | B15: ='Quarterly Data'!B13 -> 142.31
A16: 13 | B16: ='Quarterly Data'!B14 -> 177.68
